src/__init__.py
src/string_util.py
src/wallet.py
wen_evm_wallet-0.2.dist-info/METADATA
wen_evm_wallet-0.2.dist-info/WHEEL
wen_evm_wallet-0.2.dist-info/entry_points.txt
wen_evm_wallet-0.2.dist-info/top_level.txt
wen_evm_wallet-0.2.dist-info/RECORD
