Metadata-Version: 2.1
Name: wen-evm-wallet
Version: 0.2
Summary: create evm wallet
Home-page: https://github.com/av11000000/wen_evm_wallet
Author: wuwen7075
Author-email: 
License: UNKNOWN
Platform: UNKNOWN
Classifier: Programming Language :: Python :: 3
Classifier: License :: OSI Approved :: MIT License
Classifier: Operating System :: OS Independent
Requires-Dist: eth-account (==0.9.0)
